dyntftpd/__init__.py
dyntftpd/cli.py
dyntftpd/server.py
dyntftpd/handlers/__init__.py
dyntftpd/handlers/clever.py
dyntftpd/handlers/fs.py
dyntftpd/handlers/http.py
dyntftpd-0.4.0.dist-info/DESCRIPTION.rst
dyntftpd-0.4.0.dist-info/entry_points.txt
dyntftpd-0.4.0.dist-info/METADATA
dyntftpd-0.4.0.dist-info/metadata.json
dyntftpd-0.4.0.dist-info/RECORD
dyntftpd-0.4.0.dist-info/top_level.txt
dyntftpd-0.4.0.dist-info/WHEEL
tests/__init__.py
tests/test_handler_clever.py
tests/test_handler_fs.py
tests/test_handler_http.py
