Metadata-Version: 2.0
Name: dyntftpd
Version: 0.4.0
Summary: A simple TFTP server
Home-page: https://github.com/brmzkw/dyntftpd
Author: Julien Castets
Author-email: castets.j@gmail.com
License: UNKNOWN
Download-URL: https://github.com/brmzkw/dyntftpd/tarball/v0.4.0
Platform: UNKNOWN
Classifier: Development Status :: 2 - Pre-Alpha
Classifier: License :: OSI Approved :: BSD License
Classifier: Operating System :: POSIX
Classifier: Programming Language :: Python :: 2 :: Only
Classifier: Topic :: Internet :: File Transfer Protocol (FTP)
Requires-Dist: requests
